{  
    "title":"Demographics",
    "instructions":"Is this line necessary? Please answer the following questions.",
    "code":"",
    "questions":[
        {  
            "questiontype": "num_field",
            "datatype": "integer",
            "instructions": "What is your age?",
            "id": "age",
            "required":"true",
            "placeholder": "18",
            "min":"1",
            "max":"120"
        },
        {  
            "questiontype":"drop_down",
            "instructions":"Indicate your gender:",
            "id":"gender",
            "dropheight":"78",
            "required":"false",
            "items":[  
                    "woman",
                    "man",
                    "non-binary",
                    "Prefer not to disclose", 
                    "Prefer to self describe"
                ]
        },
        {
            "questiontype":"field",
            "instructions":"Self-describe your gender, if applicable:",
            "id":"gender_self_described",
            "required":false
        },
        {
        "questiontype": "slider",
        "instructions": "How much do you self-identify as a gamer on the following scale:",
        "id": "gamer_identity",
        "left": "not at all",
        "right": "gamer",
        "tick_count": 10
        },
        {
            "questiontype":"radiolist",
            "instructions":"Did you play with sound on?",
            "id":"radiolist_1",
            "labels":[
                "Yes",
                "Yes, but I could not hear the sound well",
                "I do not remember",
                "No"
            ]
        },
        {
            "questiontype":"field",
            "instructions":"Do you have any feedback related to the study?",
            "placeholder":"study feedback",
            "id":"input_1"
        },
        {
            "questiontype":"field",
            "instructions":"Do you have any feedback related to the game?",
            "placeholder":"game feedback",
            "id":"input_2"
        },
        {
            "questiontype":"field",
            "instructions":"Did you face any technical problems during the study? If yes, please describe below.",
            "placeholder":"technical feedback",
            "id":"input_3"
        }
    ]
}